ipmap/__init__.py
ipmap/cli.py
ipmap/config.py
ipmap/models.py
ipmap/datasources/__init__.py
ipmap/datasources/base.py
ipmap/datasources/cider_csv.py
ipmap/datasources/geofeed_csv.py
ipmap/datasources/maxminddb_source.py
ipmap/datasources/pcap.py
ipmap/processing/__init__.py
ipmap/processing/bucket.py
ipmap/processing/normalize.py
ipmap/processing/stats.py
ipmap/utils/__init__.py
ipmap/utils/ipmath.py
ipmap/utils/logging.py
ipmap/viz/__init__.py
ipmap/viz/export.py
ipmap/viz/heatmap.py
cider_cli-0.1.6.dist-info/METADATA
cider_cli-0.1.6.dist-info/WHEEL
cider_cli-0.1.6.dist-info/entry_points.txt
cider_cli-0.1.6.dist-info/top_level.txt
cider_cli-0.1.6.dist-info/RECORD
