Metadata-Version: 2.4
Name: cider-cli
Version: 0.1.6
Summary: IP address space visualization (pcap, geofeed, MaxMind)
Author-email: Logan Ramos <loganramos00@gmail.com>
Requires-Python: >=3.10
Requires-Dist: pandas
Requires-Dist: numpy
Requires-Dist: plotly
Requires-Dist: typer[all]
Requires-Dist: geoip2
Requires-Dist: scapy
Provides-Extra: dev
Requires-Dist: pytest; extra == "dev"
Requires-Dist: black; extra == "dev"
Requires-Dist: mypy; extra == "dev"
